alpacloud/__init__.py
alpacloud/promls/__init__.py
alpacloud/promls/__main__.py
alpacloud/promls/cli.py
alpacloud/promls/fetch.py
alpacloud/promls/filter.py
alpacloud/promls/metrics.py
alpacloud/promls/promls.css
alpacloud/promls/util.py
alpacloud/promls/vis.py
alpacloud_promls-0.3.0.dist-info/METADATA
alpacloud_promls-0.3.0.dist-info/WHEEL
alpacloud_promls-0.3.0.dist-info/entry_points.txt
alpacloud_promls-0.3.0.dist-info/namespace_packages.txt
alpacloud_promls-0.3.0.dist-info/top_level.txt
alpacloud_promls-0.3.0.dist-info/RECORD
