Metadata-Version: 2.1
Name: alpacloud_promls
Version: 0.3.0
Summary: A visualiser for available Prometheus metrics
Author: Daniel Goldman
License: Round Robin 2.0.0
Classifier: Development Status :: 3 - Alpha
Classifier: Programming Language :: Python :: 3.10
Classifier: Programming Language :: Python :: 3.11
Classifier: Programming Language :: Python :: 3.12
Classifier: Programming Language :: Python :: 3.13
Classifier: Topic :: Utilities
Classifier: Topic :: System :: Systems Administration
Requires-Python: >=3.11
Requires-Dist: click>=8.0.3
Requires-Dist: mypy~=1.16.1
Requires-Dist: requests~=2.32
Requires-Dist: textual~=5.2.0
Requires-Dist: types-PyYAML
Requires-Dist: types-requests
